RegonAPI/__init__.py
RegonAPI/api_codes.py
RegonAPI/converters.py
RegonAPI/operations.py
RegonAPI/parsers.py
RegonAPI/regon_api.py
RegonAPI/settings.py
RegonAPI/validators.py
RegonAPI/consts/__init__.py
RegonAPI/consts/api_codes.py
RegonAPI/consts/bir_version_maps.py
RegonAPI/consts/dev_environment.py
RegonAPI/consts/voivodeships.py
RegonAPI/exceptions/__init__.py
RegonAPI/exceptions/api.py
RegonAPI/exceptions/converters.py
tests/__init__.py
tests/test_api_codes.py
tests/test_converters.py
tests/test_operations.py
tests/test_parsers.py
tests/test_regon_api.py
tests/test_validators.py
RegonAPI-1.3.1.dist-info/LICENSE
RegonAPI-1.3.1.dist-info/METADATA
RegonAPI-1.3.1.dist-info/WHEEL
RegonAPI-1.3.1.dist-info/top_level.txt
RegonAPI-1.3.1.dist-info/RECORD
