Metadata-Version: 2.1
Name: RegonAPI
Version: 1.3.1
Summary: Python 3 API Client for Polish REGON database (Baza Internetowa Regon - BIR)
Home-page: https://github.com/rolzwy7/RegonAPI
Author: Bartosz Nowakowski
Author-email: rolzwy7@gmail.com
License: UNKNOWN
Platform: UNKNOWN
Classifier: Programming Language :: Python :: 3
Classifier: License :: OSI Approved :: MIT License
Classifier: Operating System :: OS Independent
Classifier: Topic :: Database :: Front-Ends
Classifier: Environment :: Console
Requires-Dist: zeep (<3.4,>=3.3)
Requires-Dist: beautifulsoup4 (<4.8,>=4.7)
